{"data":{"linksJson":{"date":"2017-08-01","links":[{"url":"https://becominghuman.ai/deep-learning-from-prototype-to-production-d2b08c85af9f","tags":["deep-learning","machine-learning","python"],"title":"Deep Learning — from Prototype to Production","domain":"becominghuman.ai"},{"url":"https://eng.uber.com/driver-profiles/","tags":["software-design","software-architecture"],"title":"Driver Profiles: How Uber Engineering Celebrates Drivers","domain":"eng.uber.com"},{"url":"https://blog.statsbot.co/machine-learning-translation-96f0ed8f19e4","tags":["deep-learning","machine-learning"],"title":"Machine Learning Translation and the Google Translate Algorithm","domain":"blog.statsbot.co"},{"url":"https://www.smashingmagazine.com/2017/08/creating-custom-inputs-vue-js/","tags":["javascript","web-frontend","vueJS"],"title":"Creating Custom Inputs With Vue.js","domain":"www.smashingmagazine.com"},{"url":"http://artsy.github.io/blog/2017/07/31/fastlane-travis-weekly-deploys/","tags":["automation","mobile","CI-CD","fastlane"],"title":"Deploying your app on a weekly basis via fastlane + Travis CI","domain":"artsy.github.io"},{"url":"https://technology.condenast.com/story/vanity-fair-game-of-unknowns","tags":["javascript","web-frontend"],"title":"How We Did It: Building \"Game of Unknowns\" on VanityFair.com","domain":"technology.condenast.com"},{"url":"https://auth0.com/blog/2016-social-passwordless-and-sso-data-what-can-we-learn/","tags":["security","auth","analytics","trends"],"title":"2016 Social, Passwordless and SSO Data: What Can We Learn?","domain":"auth0.com"},{"url":"https://robots.thoughtbot.com/lessons-from-using-phoenix-1-3","tags":["elixir","Phoenix"],"title":"Lessons From Using Phoenix 1.3","domain":"robots.thoughtbot.com"},{"url":"https://developers.soundcloud.com/blog/inside-a-soundcloud-microservice","tags":["software-architecture","infra","microservices","backend"],"title":"Inside a SoundCloud Microservice","domain":"developers.soundcloud.com"},{"url":"https://www.viget.com/articles/controlling-components-react","tags":["javascript","web-frontend","reactJS"],"title":"Controlled/Uncontrolled React Components","domain":"www.viget.com"}]}},"pageContext":{"id":"3a496e88-efd9-5397-a7f5-8b1734b5567d"}}