{"data":{"tagsJson":{"tag":"A-Frame","links":[{"url":"https://www.smashingmagazine.com/2018/11/virtual-reality-model-real-time-cross-device-preview/","tags":["VR","web","A-Frame"],"title":"How To Build A Virtual Reality Model With A Real-Time Cross-Device Preview","domain":"www.smashingmagazine.com"},{"url":"https://www.olioapps.com/blog/aframe-typescript-redux/","tags":["redux","react-VR","A-Frame"],"title":"A-Frame + Redux: Writing VR Experiences\nconnected to Redux","domain":"www.olioapps.com"},{"url":"https://www.pubnub.com/blog/build-multiplayer-browser-based-vr-game-aframe-webvr/","tags":["real-time","WebVR","A-Frame","game-dev"],"title":"Build a Multiplayer Browser-based VR Game with A-Frame, PubNub, and WebVR","domain":"www.pubnub.com"},{"url":"https://hacks.mozilla.org/2018/07/360-images-on-the-web-the-easy-way/","tags":["WebVR","A-Frame"],"title":"360° Images on the Web, the Easy Way","domain":"hacks.mozilla.org"},{"url":"https://hacks.mozilla.org/2018/03/immersive-aframe-low-poly/","tags":["javascript","WebVR","A-Frame"],"title":"Building an Immersive Game with A-Frame and Low Poly Models","domain":"hacks.mozilla.org"}]}},"pageContext":{"id":"23599529-99ff-5480-ac09-846bd6165f0e"}}