{"data":{"linksJson":{"date":"2017-08-23","links":[{"url":"https://explosion.ai/blog/pseudo-rehearsal-catastrophic-forgetting","tags":["machine-learning","API","NLP"],"title":"Pseudo-rehearsal: A simple solution to catastrophic forgetting for NLP","domain":"explosion.ai"},{"url":"https://engineering.linkedin.com/blog/2017/08/jarvis--helping-linkedin-navigate-its-source-code","tags":["dev-tools","software-engineering","compilers"],"title":"JARVIS: Helping LinkedIn Navigate its Source Code","domain":"engineering.linkedin.com"},{"url":"https://sysdig.com/blog/understanding-container-metadata/","tags":["monitoring","infra","devops","logging"],"title":"Container Metadata – Understanding Metrics, Labels, & Tags","domain":"sysdig.com"},{"url":"https://advancedweb.hu/2017/08/22/git-commit/","tags":["software-engineering","practices","git"],"title":"Git: A guide to create self-reviewed merge requests","domain":"advancedweb.hu"},{"url":"https://hacks.mozilla.org/2017/08/inside-a-super-fast-css-engine-quantum-css-aka-stylo/","tags":["optimisation","rendering","internals","css","browsers"],"title":"Inside a super fast CSS engine: Quantum CSS (aka Stylo)","domain":"hacks.mozilla.org"},{"url":"http://multithreaded.stitchfix.com/blog/2017/08/21/handling-messaging-failures/","tags":["software-architecture","infra","distributed-systems"],"title":"Understanding Failure Modes in Message and Event-based Systems","domain":"multithreaded.stitchfix.com"},{"url":"https://hashrocket.com/blog/posts/a-friendly-introduction-to-convolutional-neural-networks","tags":["AI","machine-learning","neural-net"],"title":"A Friendly Introduction to Convolutional Neural Networks","domain":"hashrocket.com"},{"url":"https://engineering.zomato.com/learnings-from-the-last-huddle-cybersecurity-684677bf86d1?source=rss----733d090d0d55---4","tags":["software-engineering","security","best-practices"],"title":"Learnings from the last Huddle: Cybersecurity","domain":"engineering.zomato.com"}]}},"pageContext":{"id":"3255d4f0-ea90-58a8-aeb2-fe5ce5fec81a"}}