{"data":{"linksJson":{"date":"2018-04-11","links":[{"url":"https://blog.imaginea.com/channels-using-async-and-await/","tags":["javascript","design-pattern","async"],"title":"Channels using async and await","domain":"blog.imaginea.com"},{"url":"https://technology.condenast.com/story/picking-trending-topics-and-celebrities-using-machine-learning","tags":["machine-learning","text-analysis"],"title":"Picking Trending Topics and Celebrities Using Machine Learning","domain":"technology.condenast.com"},{"url":"http://eng.wealthfront.com/2018/04/06/continuous-deployment-with-spark-streaming-part-i/","tags":["devops","CI-CD","apache-spark"],"title":"Continuous Deployment with Spark Streaming (Part I)","domain":"eng.wealthfront.com"},{"url":"https://www.toptal.com/spring/spring-integration-tutorial-redis-microservices","tags":["microservices","java"],"title":"Microservice Communication: A Spring Integration Tutorial with Redis","domain":"www.toptal.com"},{"url":"https://open.nytimes.com/how-we-made-the-holiday-gift-guide-72886d02b958?source=rss----51e1d1745b32---4","tags":["javascript","software-architecture","frontend"],"title":"How We Made The Holiday Gift Guide","domain":"open.nytimes.com"},{"url":"https://blog.cloudflare.com/cloudflare-argo-tunnel-with-rust-and-raspberry-pi/","tags":["CDN","networking","raspberry-pi"],"title":"Cloudflare Argo Tunnel with Rust+Raspberry Pi","domain":"blog.cloudflare.com"},{"url":"https://blog.imaginea.com/scale-part-i-task-queues/","tags":["scaling","distributed-systems","task-queue"],"title":"@Scale – Part I (Task Queues)","domain":"blog.imaginea.com"},{"url":"https://medium.com/netflix-techblog/netflix-flamescope-a57ca19d47bb?source=rss----2615bd06b42e---4","tags":["performance","data-visualisation","systems"],"title":"Netflix FlameScope","domain":"medium.com"}]}},"pageContext":{"id":"00fec305-05cc-5b44-8435-1a920e2cb04a"}}