{"data":{"tagsJson":{"tag":"bitcoin","links":[{"url":"https://medium.com/square-corner-blog/open-sourcing-subzero-ee9e3e071827?source=rss----3650599ae4e2---4","tags":["distributed-systems","opensource","bitcoin","decentralised"],"title":"Open Sourcing Subzero","domain":"medium.com"},{"url":"https://www.oreilly.com/ideas/the-blockchain-beyond-bitcoin","tags":["block-chain","bitcoin"],"title":"The blockchain beyond bitcoin","domain":"www.oreilly.com"},{"url":"https://blog.cloudflare.com/bgp-leaks-and-crypto-currencies/","tags":["security","networking","bitcoin"],"title":"BGP leaks and cryptocurrencies","domain":"blog.cloudflare.com"},{"url":"https://hackernoon.com/dissecting-the-bitcoin-whitepaper-in-four-minutes-5c8c5e5f8010?source=rss----3a8144eabfe3---4","tags":["block-chain","bitcoin"],"title":"Dissecting the Bitcoin whitepaper in four minutes","domain":"hackernoon.com"},{"url":"https://hackernoon.com/full-stack-smart-contract-development-fccdfe5176ce?source=rss----3a8144eabfe3---4","tags":["block-chain","bitcoin","DApp","ethereum"],"title":"Full-stack smart contract development","domain":"hackernoon.com"},{"url":"https://hackernoon.com/what-the-fork-a-tale-of-many-chains-72ba11ee8987?source=rss----3a8144eabfe3---4","tags":["block-chain","bitcoin"],"title":"What the fork? A tale of many chains.","domain":"hackernoon.com"},{"url":"https://hackernoon.com/heres-how-i-built-a-private-blockchain-network-and-you-can-too-62ca7db556c0?source=rss----3a8144eabfe3---4","tags":["block-chain","bitcoin"],"title":"Here’s how I built a private blockchain network, and you can too","domain":"hackernoon.com"},{"url":"https://umbrella.cisco.com/blog/2017/09/27/protecting-icos-cryptocurrency-users/","tags":["security","DNS","cryptography","bitcoin"],"title":"Protecting ICOs and cryptocurrency users","domain":"umbrella.cisco.com"},{"url":"https://spin.atomicobject.com/2017/09/06/blockchains-cryptocurrencies/","tags":["block-chain","cryptography","bitcoin"],"title":"Blockchains Explained: A Primer on Cryptocurrencies, Bitcoin, and Ethereum","domain":"spin.atomicobject.com"}]}},"pageContext":{"id":"e0cbdf81-aff8-54d6-9322-3cd2c83325cd"}}