{"data":{"tagsJson":{"tag":"edge-computing","links":[{"url":"https://blog.cloudflare.com/webassembly-on-cloudflare-workers/","tags":["web-assembly","CDN","edge-computing"],"title":"WebAssembly on Cloudflare Workers","domain":"blog.cloudflare.com"},{"url":"https://blog.cloudflare.com/building-with-workers-kv/","tags":["CDN","cloud","edge-computing"],"title":"Building With Workers KV, a Fast Distributed Key-Value Store","domain":"blog.cloudflare.com"},{"url":"https://blog.cloudflare.com/using-workers-to-make-static-sites-dynamic/","tags":["CDN","web-workers","edge-computing"],"title":"Using Workers To Make Static Sites Dynamic","domain":"blog.cloudflare.com"},{"url":"https://blog.cloudflare.com/rise-of-edge-compute-the-video/","tags":["CDN","cloud","edge-computing"],"title":"The Rise of Edge Compute: The Video","domain":"blog.cloudflare.com"}]}},"pageContext":{"id":"27e65922-3e3e-5eca-9c1a-f0cf4b9f41e6"}}