{"data":{"linksJson":{"date":"2017-07-10","links":[{"url":"http://android-developers.googleblog.com/2017/07/android-vitals-increase-engagement-and.html","tags":["performance","mobile","optimisation","android"],"title":"Android vitals: Increase engagement and installs through improved app performance","domain":"android-developers.googleblog.com"},{"url":"https://developers.redhat.com/blog/2017/07/10/using-opentracing-with-jaeger-to-collect-application-metrics-in-kubernetes/","tags":["monitoring","devops","kubernetes","analytics"],"title":"Using OpenTracing with Jaeger to collect Application Metrics in Kubernetes","domain":"developers.redhat.com"},{"url":"https://lab.getbase.com/helm-secrets-a-missing-piece-in-kubernetes/","tags":["infra","devops","containers","secrets","deployment"],"title":"Helm secrets a missing piece in Kubernetes","domain":"lab.getbase.com"},{"url":"https://realm.io/news/daniel-steinberg-altconf-2017-why-the-func/","tags":["programming-paradigm","functional-programming"],"title":"Why the Func","domain":"realm.io"},{"url":"https://blog.cloudflare.com/high-reliability-ocsp-stapling/","tags":["software-architecture","infra","web-backend","security"],"title":"High-reliability OCSP stapling and why it matters","domain":"blog.cloudflare.com"},{"url":"https://developers.redhat.com/blog/2017/07/10/configuring-containerized-services/","tags":["infra","devops","containers","deployment"],"title":"Configuring Containerized Services","domain":"developers.redhat.com"},{"url":"https://robots.thoughtbot.com/elm-glimmer","tags":["software-architecture","web-frontend","elm"],"title":"Alternative View Layers for an Elm App","domain":"robots.thoughtbot.com"},{"url":"https://spin.atomicobject.com/2017/07/08/game-playing-ai-bitboards/","tags":["AI","algorithms","game-research","data-structures"],"title":"Speed Up Your Game – Playing AI with Bitboards","domain":"spin.atomicobject.com"},{"url":"https://www.percona.com/blog/2017/07/08/mongodb-indexing-types-how-when-and-where-should-they-be-used/","tags":["DBMS","noSQL","mongoDB"],"title":"MongoDB Indexing Types: How, When and Where Should They Be Used?","domain":"www.percona.com"},{"url":"http://tech.gilt.com/ios/2017/07/07/ios-notifciation-service-extension-tips","tags":["ios","app-design","push-notification"],"title":"Advanced tips for building an iOS Notification Service Extension","domain":"tech.gilt.com"}]}},"pageContext":{"id":"31e4ed0d-b7b8-50a5-a332-d0699409531a"}}